{"type": "Feature", "id": 12517856, "properties": {"woe:id": 12517856, "woe:parent_id": 1442583, "woe:name": "El Borma Airport", "woe:placetype": 14, "woe:placetype_name": "Airport", "woe:lang": "ENG", "iso:country": "TN", "meta:provider": ["geoplanet:7.3.1", "geoplanet:7.3.2", "geoplanet:7.4.0", "geoplanet:7.4.1", "geoplanet:7.5.1", "geoplanet:7.5.2", "geoplanet:7.6.0", "geoplanet:7.8.1", "geoplanet:7.9.0", "geoplanet:7.10.0", "geoplanet:8.0.0", "woeplanet:8.0.0"], "meta:indexed": "2020-08-20T20:26:11.452911", "woe:alias_ENG_V": ["EBM Airport", "EBM"], "meta:updated": "2020-08-22T02:58:54.651148", "woe:hierarchy": {"continent": 24865670, "country": 23424967, "town": 0, "planet": 1, "county": 0, "suburb": 0, "state": 2347254, "region": 0, "localadmin": 0}, "woe:timezone_id": 28350729, "woe:hash": "sjws6ymc8xmw", "woe:centroid": [9.2694, 31.7192], "geom:latitude": 31.7192, "geom:longitude": 9.2694, "geom:hash": "sjws6ymc8xmw", "woe:latitude": 31.7192, "geom:centroid": [9.2694, 31.7192], "woe:longitude": 9.2694, "woe:repo": "woeplanet-airport-tn"}, "geometry": {"coordinates": [9.2694, 31.7192], "type": "Point"}}